README.md
setup.py
aioqiniu/__init__.py
aioqiniu/exceptions.py
aioqiniu/utils.py
aioqiniu.egg-info/PKG-INFO
aioqiniu.egg-info/SOURCES.txt
aioqiniu.egg-info/dependency_links.txt
aioqiniu.egg-info/requires.txt
aioqiniu.egg-info/top_level.txt
aioqiniu/services/__init__.py
aioqiniu/services/storage.py