Metadata-Version: 1.1
Name: aioqiniu
Version: 1.3.1
Summary: Asynchronous Qiniu Cloud Storage client based on asyncio
Home-page: https://github.com/JZQT/aioqiniu
Author: JZQT
Author-email: jzqt@witcoder.com
License: MIT
Keywords: qiniu asyncio
Platform: UNKNOWN
Classifier: Programming Language :: Python :: 3
Classifier: Programming Language :: Python :: 3.5
Classifier: Programming Language :: Python :: 3.6
Classifier: Programming Language :: Python :: 3.7
